Metadata-Version: 2.1
Name: cjkcms-color-panel
Version: 1.5.2
Summary: Forked & published on pypi for use in cjkcms and in any wagtail 6.x project that needs an updated version of wagtail-color-panel
Home-page: https://github.com/cjkpl/cjkcms-color-panel
Author: Martin Sandström. Forked by cjkpl from torchbox/wagtail-color-panel
Author-email: martin@marteinn.se
License: MIT
Classifier: Development Status :: 5 - Production/Stable
Classifier: Environment :: Web Environment
Classifier: Framework :: Django
Classifier: Framework :: Django :: 4.2
Classifier: Framework :: Django :: 5.0
Classifier: Framework :: Django :: 5.1
Classifier: Framework :: Wagtail
Classifier: Framework :: Wagtail :: 5
Classifier: Framework :: Wagtail :: 6
Classifier: Intended Audience :: Developers
Classifier: License :: OSI Approved :: MIT License
Classifier: Operating System :: OS Independent
Classifier: Programming Language :: Python
Classifier: Programming Language :: Python :: 3
Classifier: Programming Language :: Python :: 3.9
Classifier: Programming Language :: Python :: 3.10
Classifier: Programming Language :: Python :: 3.11
Classifier: Programming Language :: Python :: 3.12
Classifier: Programming Language :: Python :: 3.13
Classifier: Topic :: Utilities
Requires-Python: >=3.9
License-File: LICENSE
Requires-Dist: wagtail>=5.2
Provides-Extra: test
Requires-Dist: pytest-django; extra == "test"
Requires-Dist: wagtail-factories; extra == "test"
Requires-Dist: pytest; extra == "test"
